nphil
